LICENSE
README.md
setup.py
nanodip/__init__.py
nanodip/_jupyter.py
nanodip/api.py
nanodip/classifiers.py
nanodip/config.py
nanodip/data.py
nanodip/epidip.py
nanodip/main.py
nanodip/plots.py
nanodip/test.py
nanodip/utils.py
nanodip/webui.py
nanodip.egg-info/PKG-INFO
nanodip.egg-info/SOURCES.txt
nanodip.egg-info/dependency_links.txt
nanodip.egg-info/entry_points.txt
nanodip.egg-info/requires.txt
nanodip.egg-info/top_level.txt