Metadata-Version: 2.1
Name: nanodip
Version: 0.0.0
Summary: NanoDiP analyzes Nanopore sequencing and methylation data for tumor classification.
Home-page: https://github.com/brj0/nanodip
Author: J. Hench, C. Hultschig, J. Brugger, and S. Frank, Neuropathology IfP Basel
Classifier: Development Status :: 3 - Alpha
Classifier: Environment :: GPU :: NVIDIA CUDA
Classifier: Framework :: CherryPy
Classifier: Framework :: Jupyter :: JupyterLab
Classifier: License :: OSI Approved :: GNU General Public License v3 (GPLv3)
Classifier: Operating System :: POSIX :: Linux
Classifier: Topic :: Scientific/Engineering :: Medical Science Apps.
Classifier: Intended Audience :: Developers
Classifier: Intended Audience :: Science/Research
Classifier: Natural Language :: English
Provides-Extra: cupy
License-File: LICENSE
